textual_searchable_selectionlist/__init__.py
textual_searchable_selectionlist/options.py
textual_searchable_selectionlist/py.typed
textual_searchable_selectionlist/searchable_list_app.py
textual_searchable_selectionlist/searchable_list_widget.py
textual_searchable_selectionlist/select.py
textual_searchable_selectionlist-0.0.6.dist-info/licenses/LICENSE.txt
textual_searchable_selectionlist-0.0.6.dist-info/WHEEL
textual_searchable_selectionlist-0.0.6.dist-info/METADATA
textual_searchable_selectionlist-0.0.6.dist-info/RECORD
