Metadata-Version: 2.4
Name: textual-searchable-selectionlist
Version: 0.0.6
Summary: Add search to Textual SelectionList.
Author: Joao Coelho
Classifier: License :: OSI Approved :: MIT License
Classifier: Framework :: Pytest
Classifier: Intended Audience :: Developers
Classifier: Programming Language :: Python
Classifier: Development Status :: 5 - Production/Stable
License-File: LICENSE.txt
Requires-Dist: textual
Project-URL: Home, https://github.com/joaonc/textual-searchable-selectionlist
